bot/__init__.py
bot/bot.py
bot/manager.py
bot/project_info.py
bot/action/__init__.py
bot/action/core/__init__.py
bot/action/core/action.py
bot/action/core/filter.py
bot/action/core/update.py
bot/action/core/command/__init__.py
bot/action/core/command/no_command.py
bot/action/core/command/parser.py
bot/action/core/command/usagemessage.py
bot/action/core/command/throttler/__init__.py
bot/action/core/command/throttler/shortlyrepeatedcommand/__init__.py
bot/action/core/command/throttler/shortlyrepeatedcommand/command_key.py
bot/action/core/command/throttler/shortlyrepeatedcommand/throttler.py
bot/action/extra/__init__.py
bot/action/extra/audios.py
bot/action/extra/hashtags.py
bot/action/extra/legacypole.py
bot/action/extra/message.py
bot/action/extra/pole.py
bot/action/extra/random.py
bot/action/extra/messages/__init__.py
bot/action/extra/messages/analyzer.py
bot/action/extra/messages/mapper.py
bot/action/extra/messages/operations.py
bot/action/extra/messages/opt_out.py
bot/action/extra/messages/storage.py
bot/action/extra/messages/stored_message.py
bot/action/standard/__init__.py
bot/action/standard/about.py
bot/action/standard/answer.py
bot/action/standard/async.py
bot/action/standard/asynchronous.py
bot/action/standard/benchmark.py
bot/action/standard/enterexit.py
bot/action/standard/gapdetector.py
bot/action/standard/group_admin.py
bot/action/standard/internationalization.py
bot/action/standard/logger.py
bot/action/standard/perchat.py
bot/action/standard/silence.py
bot/action/standard/toggle.py
bot/action/standard/userinfo.py
bot/action/standard/admin/__init__.py
bot/action/standard/admin/config_status.py
bot/action/standard/admin/fail.py
bot/action/standard/admin/instance.py
bot/action/standard/admin/state.py
bot/action/standard/chatsettings/__init__.py
bot/action/standard/chatsettings/action.py
bot/action/standard/info/__init__.py
bot/action/standard/info/action.py
bot/action/standard/info/formatter/__init__.py
bot/action/standard/info/formatter/chat.py
telegram_bot_framework-3.15.2.dist-info/LICENSE
telegram_bot_framework-3.15.2.dist-info/METADATA
telegram_bot_framework-3.15.2.dist-info/WHEEL
telegram_bot_framework-3.15.2.dist-info/top_level.txt
telegram_bot_framework-3.15.2.dist-info/RECORD
