Metadata-Version: 1.2
Name: telegram-bot-framework
Version: 3.15.2
Summary: Python Telegram bot API framework
Home-page: https://github.com/alvarogzp/telegram-bot-framework
Author: Alvaro Gutierrez Perez
Author-email: alvarogzp@gmail.com
License: GNU AGPL 3.0+
Keywords: telegram bot api framework
Platform: UNKNOWN
Classifier: Development Status :: 5 - Production/Stable
Classifier: Intended Audience :: Developers
Classifier: Topic :: Software Development :: Libraries :: Application Frameworks
Classifier: License :: OSI Approved :: GNU Affero General Public License v3 or later (AGPLv3+)
Classifier: Programming Language :: Python :: 3
Classifier: Programming Language :: Python :: 3 :: Only
Classifier: Programming Language :: Python :: 3.3
Classifier: Programming Language :: Python :: 3.4
Classifier: Programming Language :: Python :: 3.5
Classifier: Programming Language :: Python :: 3.6
Requires-Python: >=3
